yfinance_timeframe_converter/__init__.py
yfinance_timeframe_converter/available_timeframes.py
yfinance_timeframe_converter/timeframe_converter.py
yfinance_timeframe_converter-1.0.2.dist-info/LICENSE.txt
yfinance_timeframe_converter-1.0.2.dist-info/METADATA
yfinance_timeframe_converter-1.0.2.dist-info/WHEEL
yfinance_timeframe_converter-1.0.2.dist-info/top_level.txt
yfinance_timeframe_converter-1.0.2.dist-info/RECORD
