Metadata-Version: 2.1
Name: yfinance-timeframe-converter
Version: 1.0.2
Summary: Converts YFinance's tables in other timeframe in an faster way
Home-page: https://github.com/LucasRocha-Png/yfinance-timeframe-converter
Author: Lucas Rocha
Author-email: lucasrocha.png@gmail.com
License: UNKNOWN
Keywords: python,yfinance,changer,yahoo,finance
Platform: UNKNOWN
Classifier: Development Status :: 5 - Production/Stable
Classifier: Intended Audience :: Developers
Classifier: Programming Language :: Python :: 3.7
Classifier: Programming Language :: C++
Classifier: License :: OSI Approved :: Apache Software License
Classifier: Operating System :: Unix
Classifier: Operating System :: Microsoft :: Windows
License-File: LICENSE.txt
Requires-Dist: pandas-datareader (>=0.10.0)
Requires-Dist: pandas (>=1.3.3)
Requires-Dist: yfinance (>=0.1.63)
